{
  "cordova-plugin-geolocation": {
    "source": {
      "type": "registry",
      "id": "cordova-plugin-geolocation@4.0.1"
    },
    "is_top_level": true,
    "variables": {}
  },
  "cordova-plugin-splashscreen": {
    "source": {
      "type": "registry",
      "id": "cordova-plugin-splashscreen@5.0.2"
    },
    "is_top_level": true,
    "variables": {}
  },
  "cordova.plugins.diagnostic": {
    "source": {
      "type": "registry",
      "id": "cordova.plugins.diagnostic@4.0.10"
    },
    "is_top_level": true,
    "variables": {}
  },
  "cordova-plugin-whitelist": {
    "source": {
      "type": "registry",
      "id": "cordova-plugin-whitelist@1"
    },
    "is_top_level": true,
    "variables": {}
  },
  "cordova-plugin-device": {
    "source": {
      "type": "registry",
      "id": "cordova-plugin-device"
    },
    "is_top_level": false,
    "variables": {}
  },
  "cordova-plugin-badge": {
    "source": {
      "type": "registry",
      "id": "cordova-plugin-badge@>=0.8.5"
    },
    "is_top_level": false,
    "variables": {}
  },
  "cordova-plugin-local-notification": {
    "source": {
      "type": "registry",
      "id": "https://github.com/Steffaan/cordova-plugin-local-notifications"
    },
    "is_top_level": true,
    "variables": {
      "ANDROID_SUPPORT_V4_VERSION": "26.+"
    }
  },
  "cordova-plugin-ble-central": {
    "source": {
      "type": "registry",
      "id": "cordova-plugin-ble-central"
    },
    "is_top_level": true,
    "variables": {
      "BLUETOOTH_USAGE_DESCRIPTION": " "
    }
  },
  "cordova-custom-config": {
    "source": {
      "type": "registry",
      "id": "cordova-custom-config"
    },
    "is_top_level": true,
    "variables": {}
  },
  "cordova-plugin-background-fetch": {
    "source": {
      "type": "registry",
      "id": "cordova-plugin-background-fetch@6.0.7"
    },
    "is_top_level": true,
    "variables": {}
  },
  "cordova-plugin-statusbar": {
    "source": {
      "type": "registry",
      "id": "https://github.com/apache/cordova-plugin-statusbar"
    },
    "is_top_level": true,
    "variables": {}
  },
  "cordova-plugin-background-mode": {
    "source": {
      "type": "registry",
      "id": "cordova-plugin-background-mode"
    },
    "is_top_level": true,
    "variables": {}
  },
  "cordova-plugin-appminimize": {
    "source": {
      "type": "registry",
      "id": "https://github.com/tomloprod/cordova-plugin-appminimize"
    },
    "is_top_level": true,
    "variables": {}
  }
}